{
  "@context": {
    "@version": 1.1,
    "@protected": true,
    "type": "@type",
    "schema": "https://schema.org/",
    "FarmerCredential": {
      "@id": "https://jainhitesh9998.github.io/tempfiles/farmer-credential-v1.json#FarmerCredential"
    },
    "dob": "schema:birthDate",
    "email": "schema:email",
    "gender": "schema:gender",
    "mobile": "schema:telephone",
    "crops": "schema:benefits",
    "fullName": "schema:name",
    "expiryDate": "schema:expires",
    "issuanceDate": "schema:DateTime",
    "landOwnershipType": "schema:Text",
    "farmerId" : "schema:Text",
    "policyNumber" : "schema:Text"
  }
}
